CHANGES
MANIFEST.in
README
crowdsourcing_requirements.txt
setup.py
crowdsourcing/__init__.py
crowdsourcing/admin.py
crowdsourcing/fields.py
crowdsourcing/flickrsupport.py
crowdsourcing/forms.py
crowdsourcing/geo.py
crowdsourcing/jsonutils.py
crowdsourcing/models.py
crowdsourcing/oembedutils.py
crowdsourcing/settings.py
crowdsourcing/tasks.py
crowdsourcing/tests.py
crowdsourcing/urls.py
crowdsourcing/util.py
crowdsourcing/views.py
crowdsourcing/templatetags/__init__.py
crowdsourcing/templatetags/crowdsourcing.py
django_crowdsourcing.egg-info/PKG-INFO
django_crowdsourcing.egg-info/SOURCES.txt
django_crowdsourcing.egg-info/dependency_links.txt
django_crowdsourcing.egg-info/top_level.txt
docs/Makefile
docs/conf.py
docs/index.rst
docs/developers/index.rst
docs/producers/ballot_stuffing.rst
docs/producers/download.rst
docs/producers/filters.rst
docs/producers/index.rst
docs/producers/live.rst
docs/producers/options.rst
docs/producers/examples/categories.rst
docs/producers/examples/favorite_composer.rst
docs/producers/examples/index.rst
docs/producers/examples/simple_poll.rst
docs/producers/examples/top_10.rst
docs/producers/examples/images/FavoriteComposerEach.png
docs/producers/examples/images/FavoriteComposerPoll.png
docs/producers/examples/images/FavoriteComposerRateOne.png
docs/producers/examples/images/FavoriteComposerRateOneReport.png
docs/producers/examples/images/LiberalConservativeReport.png
docs/producers/examples/images/LiberalConservativeSurvey.png
docs/producers/examples/images/SimplePollEntry.png
docs/producers/examples/images/SimplePollResults.png
docs/producers/examples/images/SimplePollSurvey.png
docs/producers/examples/images/Top10.png
docs/producers/images/DownloadSurveys.png