Metadata-Version: 1.0
Name: django-crowdsourcing
Version: 1.1.26
Summary: Django app for collecting and displaying surveys.
Home-page: http://code.google.com/p/django-crowdsourcing/
Author: Jacob Smullyan, Dave Smith
Author-email: jsmullyan@gmail.com
License: MIT
Platform: UNKNOWN
Classifier: Development Status :: 4 - Beta
Classifier: Framework :: Django
Classifier: License :: OSI Approved :: MIT License
